{
  "classname": null,
  "name": null,
  "animation": {
    "classname": null,
    "name": "AnimationManager",
    "actionlist": []
  },
  "dataScale": 1,
  "designHeight": 41,
  "designWidth": 313,
  "textures": [],
  "texturesPng": [
    "dec/dec_1.png"
  ],
  "version": "1.6.0.0",
  "widgetTree": {
    "classname": "Panel",
    "name": null,
    "children": [
      {
        "classname": "Panel",
        "name": null,
        "children": [
          {
            "classname": "Label",
            "name": null,
            "children": [],
            "options": {
              "__type": "LabelSurrogate:#EditorCommon.JsonModel.Component.GUI",
              "classname": "Label",
              "name": "index_txt",
              "ZOrder": 0,
              "actiontag": 32854878,
              "anchorPointX": 0.5,
              "anchorPointY": 0.5,
              "classType": "CocoStudio.EngineAdapterWrap.CSLabel",
              "colorB": 255,
              "colorG": 255,
              "colorR": 255,
              "customProperty": "",
              "flipX": false,
              "flipY": false,
              "height": 46,
              "ignoreSize": true,
              "layoutParameter": null,
              "opacity": 255,
              "positionPercentX": 0.0926517546,
              "positionPercentY": 0.4878049,
              "positionType": 0,
              "rotation": 0,
              "scaleX": 1,
              "scaleY": 1,
              "sizePercentX": 0.03514377,
              "sizePercentY": 1.12195122,
              "sizeType": 0,
              "tag": 25426,
              "touchAble": false,
              "useMergedTexture": false,
              "visible": true,
              "width": 11,
              "x": 29,
              "y": 20,
              "areaHeight": 0,
              "areaWidth": 0,
              "fontFile": null,
              "fontName": "微软雅黑",
              "fontSize": 36,
              "hAlignment": 0,
              "text": " ",
              "touchScaleEnable": false,
              "vAlignment": 0
            }
          },
          {
            "classname": "Label",
            "name": null,
            "children": [],
            "options": {
              "__type": "LabelSurrogate:#EditorCommon.JsonModel.Component.GUI",
              "classname": "Label",
              "name": "sum_txt",
              "ZOrder": 0,
              "actiontag": 45167398,
              "anchorPointX": 0.5,
              "anchorPointY": 0.5,
              "classType": "CocoStudio.EngineAdapterWrap.CSLabel",
              "colorB": 82,
              "colorG": 82,
              "colorR": 255,
              "customProperty": "",
              "flipX": false,
              "flipY": false,
              "height": 46,
              "ignoreSize": true,
              "layoutParameter": null,
              "opacity": 255,
              "positionPercentX": 0.546325862,
              "positionPercentY": 0.4878049,
              "positionType": 0,
              "rotation": 0,
              "scaleX": 1,
              "scaleY": 1,
              "sizePercentX": 0.03514377,
              "sizePercentY": 1.12195122,
              "sizeType": 0,
              "tag": 25427,
              "touchAble": false,
              "useMergedTexture": false,
              "visible": true,
              "width": 11,
              "x": 171,
              "y": 20,
              "areaHeight": 0,
              "areaWidth": 0,
              "fontFile": null,
              "fontName": "微软雅黑",
              "fontSize": 36,
              "hAlignment": 0,
              "text": " ",
              "touchScaleEnable": false,
              "vAlignment": 0
            }
          },
          {
            "classname": "Label",
            "name": null,
            "children": [],
            "options": {
              "__type": "LabelSurrogate:#EditorCommon.JsonModel.Component.GUI",
              "classname": "Label",
              "name": "type_1_txt",
              "ZOrder": 0,
              "actiontag": 3853405,
              "anchorPointX": 0.5,
              "anchorPointY": 0.5,
              "classType": "CocoStudio.EngineAdapterWrap.CSLabel",
              "colorB": 82,
              "colorG": 82,
              "colorR": 255,
              "customProperty": "",
              "flipX": false,
              "flipY": false,
              "height": 46,
              "ignoreSize": true,
              "layoutParameter": null,
              "opacity": 255,
              "positionPercentX": 0.718849838,
              "positionPercentY": 0.4878049,
              "positionType": 0,
              "rotation": 0,
              "scaleX": 1,
              "scaleY": 1,
              "sizePercentX": 0.03514377,
              "sizePercentY": 1.12195122,
              "sizeType": 0,
              "tag": 25428,
              "touchAble": false,
              "useMergedTexture": false,
              "visible": true,
              "width": 11,
              "x": 225,
              "y": 20,
              "areaHeight": 0,
              "areaWidth": 0,
              "fontFile": null,
              "fontName": "微软雅黑",
              "fontSize": 36,
              "hAlignment": 0,
              "text": " ",
              "touchScaleEnable": false,
              "vAlignment": 0
            }
          },
          {
            "classname": "Label",
            "name": null,
            "children": [],
            "options": {
              "__type": "LabelSurrogate:#EditorCommon.JsonModel.Component.GUI",
              "classname": "Label",
              "name": "type_2_txt",
              "ZOrder": 0,
              "actiontag": 34680647,
              "anchorPointX": 0.5,
              "anchorPointY": 0.5,
              "classType": "CocoStudio.EngineAdapterWrap.CSLabel",
              "colorB": 82,
              "colorG": 82,
              "colorR": 255,
              "customProperty": "",
              "flipX": false,
              "flipY": false,
              "height": 46,
              "ignoreSize": true,
              "layoutParameter": null,
              "opacity": 255,
              "positionPercentX": 0.8945687,
              "positionPercentY": 0.4878049,
              "positionType": 0,
              "rotation": 0,
              "scaleX": 1,
              "scaleY": 1,
              "sizePercentX": 0.03514377,
              "sizePercentY": 1.12195122,
              "sizeType": 0,
              "tag": 25429,
              "touchAble": false,
              "useMergedTexture": false,
              "visible": true,
              "width": 11,
              "x": 280,
              "y": 20,
              "areaHeight": 0,
              "areaWidth": 0,
              "fontFile": null,
              "fontName": "微软雅黑",
              "fontSize": 36,
              "hAlignment": 0,
              "text": " ",
              "touchScaleEnable": false,
              "vAlignment": 0
            }
          },
          {
            "classname": "ImageView",
            "name": null,
            "children": [],
            "options": {
              "__type": "ImageViewSurrogate:#EditorCommon.JsonModel.Component.GUI",
              "classname": "ImageView",
              "name": "num_1",
              "ZOrder": 0,
              "actiontag": 43690375,
              "anchorPointX": 0.5,
              "anchorPointY": 0.5,
              "classType": "CocoStudio.EngineAdapterWrap.CSImageView",
              "colorB": 255,
              "colorG": 255,
              "colorR": 255,
              "customProperty": "",
              "flipX": false,
              "flipY": false,
              "height": 53,
              "ignoreSize": true,
              "layoutParameter": null,
              "opacity": 255,
              "positionPercentX": 0.249201283,
              "positionPercentY": 0.5121951,
              "positionType": 0,
              "rotation": 0,
              "scaleX": 0.5,
              "scaleY": 0.5,
              "sizePercentX": 0.17252396,
              "sizePercentY": 1.29268289,
              "sizeType": 0,
              "tag": 25430,
              "touchAble": false,
              "useMergedTexture": false,
              "visible": true,
              "width": 54,
              "x": 78,
              "y": 21,
              "capInsetsHeight": 1,
              "capInsetsWidth": 1,
              "capInsetsX": 0,
              "capInsetsY": 0,
              "fileName": null,
              "fileNameData": {
                "path": "dec/dec_1.png",
                "plistFile": "",
                "resourceType": 0
              },
              "scale9Enable": false,
              "scale9Height": 53,
              "scale9Width": 54
            }
          },
          {
            "classname": "ImageView",
            "name": null,
            "children": [],
            "options": {
              "__type": "ImageViewSurrogate:#EditorCommon.JsonModel.Component.GUI",
              "classname": "ImageView",
              "name": "num_2",
              "ZOrder": 0,
              "actiontag": 57669061,
              "anchorPointX": 0.5,
              "anchorPointY": 0.5,
              "classType": "CocoStudio.EngineAdapterWrap.CSImageView",
              "colorB": 255,
              "colorG": 255,
              "colorR": 255,
              "customProperty": "",
              "flipX": false,
              "flipY": false,
              "height": 53,
              "ignoreSize": true,
              "layoutParameter": null,
              "opacity": 255,
              "positionPercentX": 0.341853023,
              "positionPercentY": 0.5121951,
              "positionType": 0,
              "rotation": 0,
              "scaleX": 0.5,
              "scaleY": 0.5,
              "sizePercentX": 0.17252396,
              "sizePercentY": 1.29268289,
              "sizeType": 0,
              "tag": 25431,
              "touchAble": false,
              "useMergedTexture": false,
              "visible": true,
              "width": 54,
              "x": 107,
              "y": 21,
              "capInsetsHeight": 1,
              "capInsetsWidth": 1,
              "capInsetsX": 0,
              "capInsetsY": 0,
              "fileName": null,
              "fileNameData": {
                "path": "dec/dec_1.png",
                "plistFile": "",
                "resourceType": 0
              },
              "scale9Enable": false,
              "scale9Height": 53,
              "scale9Width": 54
            }
          },
          {
            "classname": "ImageView",
            "name": null,
            "children": [],
            "options": {
              "__type": "ImageViewSurrogate:#EditorCommon.JsonModel.Component.GUI",
              "classname": "ImageView",
              "name": "num_3",
              "ZOrder": 0,
              "actiontag": 49259506,
              "anchorPointX": 0.5,
              "anchorPointY": 0.5,
              "classType": "CocoStudio.EngineAdapterWrap.CSImageView",
              "colorB": 255,
              "colorG": 255,
              "colorR": 255,
              "customProperty": "",
              "flipX": false,
              "flipY": false,
              "height": 53,
              "ignoreSize": true,
              "layoutParameter": null,
              "opacity": 255,
              "positionPercentX": 0.437699676,
              "positionPercentY": 0.5121951,
              "positionType": 0,
              "rotation": 0,
              "scaleX": 0.5,
              "scaleY": 0.5,
              "sizePercentX": 0.17252396,
              "sizePercentY": 1.29268289,
              "sizeType": 0,
              "tag": 25432,
              "touchAble": false,
              "useMergedTexture": false,
              "visible": true,
              "width": 54,
              "x": 137,
              "y": 21,
              "capInsetsHeight": 1,
              "capInsetsWidth": 1,
              "capInsetsX": 0,
              "capInsetsY": 0,
              "fileName": null,
              "fileNameData": {
                "path": "dec/dec_1.png",
                "plistFile": "",
                "resourceType": 0
              },
              "scale9Enable": false,
              "scale9Height": 53,
              "scale9Width": 54
            }
          }
        ],
        "options": {
          "__type": "PanelSurrogate:#EditorCommon.JsonModel.Component.GUI",
          "classname": "Panel",
          "name": "content_view",
          "ZOrder": 0,
          "actiontag": 51980066,
          "anchorPointX": 0,
          "anchorPointY": 0,
          "classType": "CocoStudio.EngineAdapterWrap.CSPanel",
          "colorB": 255,
          "colorG": 255,
          "colorR": 255,
          "customProperty": "",
          "flipX": false,
          "flipY": false,
          "height": 41,
          "ignoreSize": false,
          "layoutParameter": null,
          "opacity": 255,
          "positionPercentX": 0,
          "positionPercentY": 0,
          "positionType": 0,
          "rotation": 0,
          "scaleX": 1,
          "scaleY": 1,
          "sizePercentX": 1,
          "sizePercentY": 1,
          "sizeType": 0,
          "tag": 25425,
          "touchAble": true,
          "useMergedTexture": false,
          "visible": true,
          "width": 313,
          "x": 0,
          "y": 0,
          "adaptScreen": false,
          "backGroundImage": null,
          "backGroundImageData": null,
          "backGroundScale9Enable": false,
          "bgColorB": 255,
          "bgColorG": 200,
          "bgColorOpacity": 100,
          "bgColorR": 150,
          "bgEndColorB": 255,
          "bgEndColorG": 200,
          "bgEndColorR": 150,
          "bgStartColorB": 255,
          "bgStartColorG": 255,
          "bgStartColorR": 255,
          "capInsetsHeight": 1,
          "capInsetsWidth": 1,
          "capInsetsX": 0,
          "capInsetsY": 0,
          "clipAble": false,
          "colorType": 0,
          "layoutType": 0,
          "vectorX": 0,
          "vectorY": -0.5
        }
      }
    ],
    "options": {
      "__type": "PanelSurrogate:#EditorCommon.JsonModel.Component.GUI",
      "classname": "Panel",
      "name": "Panel_29",
      "ZOrder": 0,
      "actiontag": -1,
      "anchorPointX": 0,
      "anchorPointY": 0,
      "classType": "CocoStudio.EngineAdapterWrap.CSPanel",
      "colorB": 255,
      "colorG": 255,
      "colorR": 255,
      "customProperty": "",
      "flipX": false,
      "flipY": false,
      "height": 41,
      "ignoreSize": false,
      "layoutParameter": null,
      "opacity": 255,
      "positionPercentX": 0,
      "positionPercentY": 0,
      "positionType": 0,
      "rotation": 0,
      "scaleX": 1,
      "scaleY": 1,
      "sizePercentX": 1,
      "sizePercentY": 1,
      "sizeType": 0,
      "tag": 25408,
      "touchAble": true,
      "useMergedTexture": false,
      "visible": true,
      "width": 313,
      "x": 0,
      "y": 0,
      "adaptScreen": false,
      "backGroundImage": null,
      "backGroundImageData": null,
      "backGroundScale9Enable": false,
      "bgColorB": 255,
      "bgColorG": 200,
      "bgColorOpacity": 0,
      "bgColorR": 150,
      "bgEndColorB": 255,
      "bgEndColorG": 200,
      "bgEndColorR": 150,
      "bgStartColorB": 255,
      "bgStartColorG": 255,
      "bgStartColorR": 255,
      "capInsetsHeight": 1,
      "capInsetsWidth": 1,
      "capInsetsX": 0,
      "capInsetsY": 0,
      "clipAble": false,
      "colorType": 1,
      "layoutType": 0,
      "vectorX": 0,
      "vectorY": -0.5
    }
  }
}