{
  "classname": null,
  "name": null,
  "animation": {
    "classname": null,
    "name": "AnimationManager",
    "actionlist": []
  },
  "dataScale": 1,
  "designHeight": 720,
  "designWidth": 1280,
  "textures": [],
  "texturesPng": [],
  "version": "1.6.0.0",
  "widgetTree": {
    "classname": "Panel",
    "name": null,
    "children": [
      {
        "classname": "ImageView",
        "name": null,
        "children": [
          {
            "classname": "ImageView",
            "name": null,
            "children": [],
            "options": {
              "__type": "ImageViewSurrogate:#EditorCommon.JsonModel.Component.GUI",
              "classname": "ImageView",
              "name": "title_icon",
              "ZOrder": 0,
              "actiontag": 10259005,
              "anchorPointX": 0.5,
              "anchorPointY": 0.5,
              "classType": "CocoStudio.EngineAdapterWrap.CSImageView",
              "colorB": 255,
              "colorG": 255,
              "colorR": 255,
              "customProperty": "",
              "flipX": false,
              "flipY": false,
              "height": 94,
              "ignoreSize": true,
              "layoutParameter": null,
              "opacity": 255,
              "positionPercentX": 0.0328125,
              "positionPercentY": 0.4097222,
              "positionType": 0,
              "rotation": 0,
              "scaleX": 1,
              "scaleY": 1,
              "sizePercentX": 0.4265625,
              "sizePercentY": 0.130555555,
              "sizeType": 0,
              "tag": 19925,
              "touchAble": false,
              "useMergedTexture": false,
              "visible": true,
              "width": 546,
              "x": 42,
              "y": 295,
              "capInsetsHeight": 1,
              "capInsetsWidth": 1,
              "capInsetsX": 0,
              "capInsetsY": 0,
              "fileName": null,
              "fileNameData": {
                "path": "fonts/nogold.png",
                "plistFile": "",
                "resourceType": 0
              },
              "scale9Enable": false,
              "scale9Height": 94,
              "scale9Width": 546
            }
          },
          {
            "classname": "ImageView",
            "name": null,
            "children": [
              {
                "classname": "ImageView",
                "name": null,
                "children": [],
                "options": {
                  "__type": "ImageViewSurrogate:#EditorCommon.JsonModel.Component.GUI",
                  "classname": "ImageView",
                  "name": "gold_plate",
                  "ZOrder": 0,
                  "actiontag": 41737539,
                  "anchorPointX": 0.5,
                  "anchorPointY": 0.5,
                  "classType": "CocoStudio.EngineAdapterWrap.CSImageView",
                  "colorB": 255,
                  "colorG": 255,
                  "colorR": 255,
                  "customProperty": "",
                  "flipX": false,
                  "flipY": false,
                  "height": 193,
                  "ignoreSize": true,
                  "layoutParameter": null,
                  "opacity": 255,
                  "positionPercentX": 0.00157356414,
                  "positionPercentY": 0.0657439455,
                  "positionType": 0,
                  "rotation": 0,
                  "scaleX": 1,
                  "scaleY": 1,
                  "sizePercentX": 0.476789922,
                  "sizePercentY": 0.333910048,
                  "sizeType": 0,
                  "tag": 18445,
                  "touchAble": false,
                  "useMergedTexture": false,
                  "visible": true,
                  "width": 606,
                  "x": 2,
                  "y": 38,
                  "capInsetsHeight": 1,
                  "capInsetsWidth": 1,
                  "capInsetsX": 0,
                  "capInsetsY": 0,
                  "fileName": null,
                  "fileNameData": {
                    "path": "icon/gold_plate.png",
                    "plistFile": "",
                    "resourceType": 0
                  },
                  "scale9Enable": false,
                  "scale9Height": 193,
                  "scale9Width": 606
                }
              },
              {
                "classname": "ImageView",
                "name": null,
                "children": [],
                "options": {
                  "__type": "ImageViewSurrogate:#EditorCommon.JsonModel.Component.GUI",
                  "classname": "ImageView",
                  "name": "chip_stack",
                  "ZOrder": 0,
                  "actiontag": 22021759,
                  "anchorPointX": 0.5,
                  "anchorPointY": 0.5,
                  "classType": "CocoStudio.EngineAdapterWrap.CSImageView",
                  "colorB": 255,
                  "colorG": 255,
                  "colorR": 255,
                  "customProperty": "",
                  "flipX": false,
                  "flipY": false,
                  "height": 265,
                  "ignoreSize": true,
                  "layoutParameter": null,
                  "opacity": 255,
                  "positionPercentX": -0.0582218729,
                  "positionPercentY": 0.129757792,
                  "positionType": 0,
                  "rotation": 0,
                  "scaleX": 1,
                  "scaleY": 1,
                  "sizePercentX": 0.334382385,
                  "sizePercentY": 0.4584775,
                  "sizeType": 0,
                  "tag": 18446,
                  "touchAble": false,
                  "useMergedTexture": false,
                  "visible": true,
                  "width": 425,
                  "x": -74,
                  "y": 75,
                  "capInsetsHeight": 1,
                  "capInsetsWidth": 1,
                  "capInsetsX": 0,
                  "capInsetsY": 0,
                  "fileName": null,
                  "fileNameData": {
                    "path": "icon/icon_chip_stack.png",
                    "plistFile": "",
                    "resourceType": 0
                  },
                  "scale9Enable": false,
                  "scale9Height": 265,
                  "scale9Width": 425
                }
              },
              {
                "classname": "ImageView",
                "name": null,
                "children": [],
                "options": {
                  "__type": "ImageViewSurrogate:#EditorCommon.JsonModel.Component.GUI",
                  "classname": "ImageView",
                  "name": "banner",
                  "ZOrder": 0,
                  "actiontag": 21989162,
                  "anchorPointX": 0.5,
                  "anchorPointY": 0.5,
                  "classType": "CocoStudio.EngineAdapterWrap.CSImageView",
                  "colorB": 255,
                  "colorG": 255,
                  "colorR": 255,
                  "customProperty": "",
                  "flipX": false,
                  "flipY": false,
                  "height": 133,
                  "ignoreSize": true,
                  "layoutParameter": null,
                  "opacity": 255,
                  "positionPercentX": 0.00472069252,
                  "positionPercentY": -0.0328719728,
                  "positionType": 0,
                  "rotation": 0,
                  "scaleX": 1,
                  "scaleY": 1,
                  "sizePercentX": 0.6050354,
                  "sizePercentY": 0.2301038,
                  "sizeType": 0,
                  "tag": 18449,
                  "touchAble": false,
                  "useMergedTexture": false,
                  "visible": true,
                  "width": 769,
                  "x": 6,
                  "y": -19,
                  "capInsetsHeight": 1,
                  "capInsetsWidth": 1,
                  "capInsetsX": 0,
                  "capInsetsY": 0,
                  "fileName": null,
                  "fileNameData": {
                    "path": "dec/dec_banner.png",
                    "plistFile": "",
                    "resourceType": 0
                  },
                  "scale9Enable": false,
                  "scale9Height": 133,
                  "scale9Width": 769
                }
              },
              {
                "classname": "Panel",
                "name": null,
                "children": [],
                "options": {
                  "__type": "PanelSurrogate:#EditorCommon.JsonModel.Component.GUI",
                  "classname": "Panel",
                  "name": "num_handler",
                  "ZOrder": 0,
                  "actiontag": 34607923,
                  "anchorPointX": 0,
                  "anchorPointY": 0,
                  "classType": "CocoStudio.EngineAdapterWrap.CSPanel",
                  "colorB": 255,
                  "colorG": 255,
                  "colorR": 255,
                  "customProperty": "",
                  "flipX": false,
                  "flipY": false,
                  "height": 46,
                  "ignoreSize": false,
                  "layoutParameter": null,
                  "opacity": 255,
                  "positionPercentX": 0.00472069252,
                  "positionPercentY": -0.115916952,
                  "positionType": 0,
                  "rotation": 0,
                  "scaleX": 1,
                  "scaleY": 1,
                  "sizePercentX": 0.01888277,
                  "sizePercentY": 0.07958478,
                  "sizeType": 0,
                  "tag": 18450,
                  "touchAble": true,
                  "useMergedTexture": false,
                  "visible": true,
                  "width": 24,
                  "x": 6,
                  "y": -67,
                  "adaptScreen": false,
                  "backGroundImage": null,
                  "backGroundImageData": null,
                  "backGroundScale9Enable": false,
                  "bgColorB": 255,
                  "bgColorG": 200,
                  "bgColorOpacity": 100,
                  "bgColorR": 150,
                  "bgEndColorB": 255,
                  "bgEndColorG": 200,
                  "bgEndColorR": 150,
                  "bgStartColorB": 255,
                  "bgStartColorG": 255,
                  "bgStartColorR": 255,
                  "capInsetsHeight": 1,
                  "capInsetsWidth": 1,
                  "capInsetsX": 0,
                  "capInsetsY": 0,
                  "clipAble": false,
                  "colorType": 0,
                  "layoutType": 0,
                  "vectorX": 0,
                  "vectorY": -0.5
                }
              },
              {
                "classname": "Label",
                "name": null,
                "children": [],
                "options": {
                  "__type": "LabelSurrogate:#EditorCommon.JsonModel.Component.GUI",
                  "classname": "Label",
                  "name": "recommend_desc_txt",
                  "ZOrder": 0,
                  "actiontag": 5360259,
                  "anchorPointX": 0.5,
                  "anchorPointY": 0.5,
                  "classType": "CocoStudio.EngineAdapterWrap.CSLabel",
                  "colorB": 255,
                  "colorG": 255,
                  "colorR": 255,
                  "customProperty": "",
                  "flipX": false,
                  "flipY": false,
                  "height": 57,
                  "ignoreSize": true,
                  "layoutParameter": null,
                  "opacity": 255,
                  "positionPercentX": 0,
                  "positionPercentY": -0.19550173,
                  "positionType": 0,
                  "rotation": 0,
                  "scaleX": 1,
                  "scaleY": 1,
                  "sizePercentX": 0.0102281664,
                  "sizePercentY": 0.0986159146,
                  "sizeType": 0,
                  "tag": 18452,
                  "touchAble": false,
                  "useMergedTexture": false,
                  "visible": true,
                  "width": 13,
                  "x": 0,
                  "y": -113,
                  "areaHeight": 0,
                  "areaWidth": 0,
                  "fontFile": null,
                  "fontName": "微软雅黑",
                  "fontSize": 43,
                  "hAlignment": 0,
                  "text": " ",
                  "touchScaleEnable": false,
                  "vAlignment": 0
                }
              },
              {
                "classname": "Button",
                "name": null,
                "children": [],
                "options": {
                  "__type": "ButtonSurrogate:#EditorCommon.JsonModel.Component.GUI",
                  "classname": "Button",
                  "name": "buy_btn",
                  "ZOrder": 0,
                  "actiontag": 10916771,
                  "anchorPointX": 0.5,
                  "anchorPointY": 0.5,
                  "classType": "CocoStudio.EngineAdapterWrap.CSButton",
                  "colorB": 255,
                  "colorG": 255,
                  "colorR": 255,
                  "customProperty": "",
                  "flipX": false,
                  "flipY": false,
                  "height": 77,
                  "ignoreSize": true,
                  "layoutParameter": null,
                  "opacity": 255,
                  "positionPercentX": 0.007867821,
                  "positionPercentY": -0.3252595,
                  "positionType": 0,
                  "rotation": 0,
                  "scaleX": 1,
                  "scaleY": 1,
                  "sizePercentX": 0.196695521,
                  "sizePercentY": 0.13321799,
                  "sizeType": 0,
                  "tag": 18451,
                  "touchAble": true,
                  "useMergedTexture": false,
                  "visible": true,
                  "width": 250,
                  "x": 10,
                  "y": -188,
                  "capInsetsHeight": 1,
                  "capInsetsWidth": 1,
                  "capInsetsX": 0,
                  "capInsetsY": 0,
                  "disabled": null,
                  "disabledData": {
                    "path": null,
                    "plistFile": null,
                    "resourceType": 0
                  },
                  "fontName": "微软雅黑",
                  "fontSize": 14,
                  "fontType": 0,
                  "normal": null,
                  "normalData": {
                    "path": "btn/btn_yes3_nor.png",
                    "plistFile": "",
                    "resourceType": 0
                  },
                  "pressed": null,
                  "pressedData": {
                    "path": "btn/btn_yes3_pre.png",
                    "plistFile": "",
                    "resourceType": 0
                  },
                  "scale9Enable": false,
                  "scale9Height": 77,
                  "scale9Width": 250,
                  "text": "",
                  "textColorB": 255,
                  "textColorG": 255,
                  "textColorR": 255
                }
              }
            ],
            "options": {
              "__type": "ImageViewSurrogate:#EditorCommon.JsonModel.Component.GUI",
              "classname": "ImageView",
              "name": "recommend_bg",
              "ZOrder": 0,
              "actiontag": 59641172,
              "anchorPointX": 0.5,
              "anchorPointY": 0.5,
              "classType": "CocoStudio.EngineAdapterWrap.CSImageView",
              "colorB": 255,
              "colorG": 255,
              "colorR": 255,
              "customProperty": "",
              "flipX": false,
              "flipY": false,
              "height": 578,
              "ignoreSize": true,
              "layoutParameter": null,
              "opacity": 255,
              "positionPercentX": 0,
              "positionPercentY": -0.0597222224,
              "positionType": 0,
              "rotation": 0,
              "scaleX": 1,
              "scaleY": 1,
              "sizePercentX": 0.992968738,
              "sizePercentY": 0.802777767,
              "sizeType": 0,
              "tag": 18443,
              "touchAble": false,
              "useMergedTexture": false,
              "visible": true,
              "width": 1271,
              "x": 0,
              "y": -43,
              "capInsetsHeight": 1,
              "capInsetsWidth": 1,
              "capInsetsX": 0,
              "capInsetsY": 0,
              "fileName": null,
              "fileNameData": {
                "path": "bg/bg_nogold3.png",
                "plistFile": "",
                "resourceType": 0
              },
              "scale9Enable": false,
              "scale9Height": 578,
              "scale9Width": 1271
            }
          },
          {
            "classname": "Button",
            "name": null,
            "children": [],
            "options": {
              "__type": "ButtonSurrogate:#EditorCommon.JsonModel.Component.GUI",
              "classname": "Button",
              "name": "close_btn",
              "ZOrder": 0,
              "actiontag": 2597469,
              "anchorPointX": 0.5,
              "anchorPointY": 0.5,
              "classType": "CocoStudio.EngineAdapterWrap.CSButton",
              "colorB": 255,
              "colorG": 255,
              "colorR": 255,
              "customProperty": "",
              "flipX": false,
              "flipY": false,
              "height": 72,
              "ignoreSize": true,
              "layoutParameter": null,
              "opacity": 255,
              "positionPercentX": 0.425,
              "positionPercentY": 0.4027778,
              "positionType": 0,
              "rotation": 0,
              "scaleX": 1,
              "scaleY": 1,
              "sizePercentX": 0.07578125,
              "sizePercentY": 0.1,
              "sizeType": 0,
              "tag": 18448,
              "touchAble": true,
              "useMergedTexture": false,
              "visible": true,
              "width": 97,
              "x": 544,
              "y": 290,
              "capInsetsHeight": 1,
              "capInsetsWidth": 1,
              "capInsetsX": 0,
              "capInsetsY": 0,
              "disabled": null,
              "disabledData": {
                "path": null,
                "plistFile": null,
                "resourceType": 0
              },
              "fontName": "微软雅黑",
              "fontSize": 14,
              "fontType": 0,
              "normal": null,
              "normalData": {
                "path": "btn/btn_close_nor.png",
                "plistFile": "",
                "resourceType": 0
              },
              "pressed": null,
              "pressedData": {
                "path": "btn/btn_close_pre.png",
                "plistFile": "",
                "resourceType": 0
              },
              "scale9Enable": false,
              "scale9Height": 72,
              "scale9Width": 97,
              "text": "",
              "textColorB": 255,
              "textColorG": 255,
              "textColorR": 255
            }
          }
        ],
        "options": {
          "__type": "ImageViewSurrogate:#EditorCommon.JsonModel.Component.GUI",
          "classname": "ImageView",
          "name": "content_bg",
          "ZOrder": 0,
          "actiontag": 56646304,
          "anchorPointX": 0.5,
          "anchorPointY": 0.5,
          "classType": "CocoStudio.EngineAdapterWrap.CSImageView",
          "colorB": 255,
          "colorG": 255,
          "colorR": 255,
          "customProperty": "",
          "flipX": false,
          "flipY": false,
          "height": 720,
          "ignoreSize": true,
          "layoutParameter": null,
          "opacity": 255,
          "positionPercentX": 0.5,
          "positionPercentY": 0.5,
          "positionType": 0,
          "rotation": 0,
          "scaleX": 1,
          "scaleY": 1,
          "sizePercentX": 1,
          "sizePercentY": 1,
          "sizeType": 0,
          "tag": 18441,
          "touchAble": false,
          "useMergedTexture": false,
          "visible": true,
          "width": 1280,
          "x": 640,
          "y": 360,
          "capInsetsHeight": 1,
          "capInsetsWidth": 1,
          "capInsetsX": 0,
          "capInsetsY": 0,
          "fileName": null,
          "fileNameData": {
            "path": "bg/bg_nogold.png",
            "plistFile": "",
            "resourceType": 0
          },
          "scale9Enable": false,
          "scale9Height": 720,
          "scale9Width": 1280
        }
      }
    ],
    "options": {
      "__type": "PanelSurrogate:#EditorCommon.JsonModel.Component.GUI",
      "classname": "Panel",
      "name": "Panel_28",
      "ZOrder": 0,
      "actiontag": -1,
      "anchorPointX": 0,
      "anchorPointY": 0,
      "classType": "CocoStudio.EngineAdapterWrap.CSPanel",
      "colorB": 255,
      "colorG": 255,
      "colorR": 255,
      "customProperty": "",
      "flipX": false,
      "flipY": false,
      "height": 720,
      "ignoreSize": false,
      "layoutParameter": null,
      "opacity": 255,
      "positionPercentX": 0,
      "positionPercentY": 0,
      "positionType": 0,
      "rotation": 0,
      "scaleX": 1,
      "scaleY": 1,
      "sizePercentX": 1,
      "sizePercentY": 1,
      "sizeType": 0,
      "tag": 18440,
      "touchAble": true,
      "useMergedTexture": false,
      "visible": true,
      "width": 1280,
      "x": 0,
      "y": 0,
      "adaptScreen": false,
      "backGroundImage": null,
      "backGroundImageData": {
        "path": "dec/deck_mask.png",
        "plistFile": "",
        "resourceType": 0
      },
      "backGroundScale9Enable": false,
      "bgColorB": 255,
      "bgColorG": 200,
      "bgColorOpacity": 0,
      "bgColorR": 150,
      "bgEndColorB": 255,
      "bgEndColorG": 200,
      "bgEndColorR": 150,
      "bgStartColorB": 255,
      "bgStartColorG": 255,
      "bgStartColorR": 255,
      "capInsetsHeight": 1,
      "capInsetsWidth": 1,
      "capInsetsX": 0,
      "capInsetsY": 0,
      "clipAble": false,
      "colorType": 0,
      "layoutType": 0,
      "vectorX": 0,
      "vectorY": -0.5
    }
  }
}